pystiler/__init__.py
pystiler/api.py
pystiler/screen.py
pystiler/workspaces.py
pystiler-0.4.0.dist-info/DESCRIPTION.rst
pystiler-0.4.0.dist-info/METADATA
pystiler-0.4.0.dist-info/RECORD
pystiler-0.4.0.dist-info/WHEEL
pystiler-0.4.0.dist-info/entry_points.txt
pystiler-0.4.0.dist-info/metadata.json
pystiler-0.4.0.dist-info/top_level.txt
