Metadata-Version: 2.0
Name: pystiler
Version: 0.4.0
Summary: Python simple tiler for non-tiling window managers
Home-page: http://github.com/riley-martine/pyst
Author: Riley Martine
Author-email: riley.martine.0@gmail.com
License: MIT
Keywords: window-manager tiling wm command-line cli
Platform: UNKNOWN
Classifier: Development Status :: 3 - Alpha
Classifier: Environment :: X11 Applications
Classifier: Intended Audience :: Developers
Classifier: License :: OSI Approved :: MIT License
Classifier: Natural Language :: English
Classifier: Operating System :: Unix
Classifier: Programming Language :: Python :: 3.6
Classifier: Topic :: Desktop Environment :: Window Managers
